testing.rabbitmq-1.0.2-py3.9-nspkg.pth
testing/rabbitmq.py
testing.rabbitmq-1.0.2.dist-info/LICENSE
testing.rabbitmq-1.0.2.dist-info/METADATA
testing.rabbitmq-1.0.2.dist-info/WHEEL
testing.rabbitmq-1.0.2.dist-info/namespace_packages.txt
testing.rabbitmq-1.0.2.dist-info/top_level.txt
testing.rabbitmq-1.0.2.dist-info/RECORD
