Metadata-Version: 2.1
Name: testing.rabbitmq
Version: 1.0.2
Summary: automatically setups a rabbitmq server instance for use in tests
Home-page: https://github.com/tristan/testing.rabbitmq
Author: Tristan King
Author-email: mail@tristan.sh
License: Apache License 2.0
Platform: UNKNOWN
Classifier: Development Status :: 4 - Beta
Classifier: Intended Audience :: Developers
Classifier: License :: OSI Approved :: Apache Software License
Classifier: Programming Language :: Python
Classifier: Programming Language :: Python :: 2.6
Classifier: Programming Language :: Python :: 2.7
Classifier: Programming Language :: Python :: 3.2
Classifier: Programming Language :: Python :: 3.3
Classifier: Programming Language :: Python :: 3.4
Classifier: Programming Language :: Python :: 3.5
Classifier: Programming Language :: Python :: 3.6
Classifier: Programming Language :: Python :: 3.7
Classifier: Topic :: Database
Classifier: Topic :: Software Development
Classifier: Topic :: Software Development :: Testing
License-File: LICENSE
Requires-Dist: testing.common.database (>=1.1.0)
Requires-Dist: psutil
